{
  "generated_at": "2026-05-20T14:05:09.666309",
  "version": "3.86",
  "scan_hours": 72,
  "retention_days": 7,
  "activities": [
    {
      "activity_id": "i148301477",
      "date": "2026-05-14",
      "type": "VirtualRide",
      "name": "Sweet Spot B #4",
      "interval_summary": [
        "1x 6m 103w",
        "1x 4m1s 129w",
        "4x 3m 171w",
        "3x 2m 185w",
        "1x 60s 192w",
        "1x 15s 260w",
        "1x 45s 157w",
        "2x 60s 104w",
        "4x 3m 213w",
        "2x 2m 103w",
        "2x 2m 131w",
        "1x 3m 104w",
        "1x 60s 131w"
      ],
      "intervals": [
        {
          "type": "WORK",
          "label": "360s@103w83rpm",
          "duration_secs": 360,
          "avg_power": 103,
          "max_power": 162,
          "avg_hr": 103,
          "max_hr": 115,
          "avg_cadence": 82.566666,
          "zone": 1,
          "training_load": 1.7660875,
          "decoupling": 2.3009202
        },
        {
          "type": "WORK",
          "label": "241s@129w88rpm",
          "duration_secs": 241,
          "avg_power": 129,
          "max_power": 152,
          "avg_hr": 114,
          "max_hr": 127,
          "avg_cadence": 88.13278,
          "zone": 1,
          "training_load": 1.9041976,
          "decoupling": 3.0315545
        },
        {
          "type": "WORK",
          "label": "180s@171w94rpm",
          "duration_secs": 180,
          "avg_power": 155,
          "max_power": 185,
          "avg_hr": 120,
          "max_hr": 126,
          "avg_cadence": 91.72222,
          "zone": 1,
          "training_load": 2.0586805,
          "decoupling": 1.6990064
        },
        {
          "type": "WORK",
          "label": "120s@185w92rpm",
          "duration_secs": 120,
          "avg_power": 168,
          "max_power": 203,
          "avg_hr": 130,
          "max_hr": 137,
          "avg_cadence": 91.34167,
          "zone": 1,
          "training_load": 1.6139468,
          "decoupling": 0.03302634
        },
        {
          "type": "WORK",
          "label": "60s@192w93rpm",
          "duration_secs": 60,
          "avg_power": 192,
          "max_power": 247,
          "avg_hr": 133,
          "max_hr": 137,
          "avg_cadence": 92.61667,
          "zone": 2,
          "training_load": 1.0226852,
          "decoupling": 3.630009
        },
        {
          "type": "WORK",
          "label": "15s@260w91rpm",
          "duration_secs": 15,
          "avg_power": 260,
          "max_power": 304,
          "avg_hr": 135,
          "max_hr": 138,
          "avg_cadence": 91.333336,
          "zone": 6,
          "training_load": 0.32205585,
          "decoupling": 5.7784114
        },
        {
          "type": "WORK",
          "label": "45s@157w92rpm",
          "duration_secs": 45,
          "avg_power": 157,
          "max_power": 265,
          "avg_hr": 138,
          "max_hr": 141,
          "avg_cadence": 91.91111,
          "zone": 1,
          "training_load": 0.80835503,
          "decoupling": 3.32778
        },
        {
          "type": "WORK",
          "label": "60s@104w90rpm",
          "duration_secs": 60,
          "avg_power": 106,
          "max_power": 127,
          "avg_hr": 125,
          "max_hr": 137,
          "avg_cadence": 90.166664,
          "zone": 1,
          "training_load": 0.41666666,
          "decoupling": -16.019703
        },
        {
          "type": "WORK",
          "label": "180s@171w94rpm",
          "duration_secs": 180,
          "avg_power": 180,
          "max_power": 239,
          "avg_hr": 130,
          "max_hr": 141,
          "avg_cadence": 93.26667,
          "zone": 2,
          "training_load": 2.7195313,
          "decoupling": 6.687556
        },
        {
          "type": "WORK",
          "label": "120s@185w92rpm",
          "duration_secs": 120,
          "avg_power": 201,
          "max_power": 258,
          "avg_hr": 140,
          "max_hr": 146,
          "avg_cadence": 93.816666,
          "zone": 3,
          "training_load": 2.2917244,
          "decoupling": 1.8777976
        },
        {
          "type": "WORK",
          "label": "180s@213w94rpm",
          "duration_secs": 180,
          "avg_power": 217,
          "max_power": 281,
          "avg_hr": 148,
          "max_hr": 153,
          "avg_cadence": 95.70556,
          "zone": 3,
          "training_load": 4.05,
          "decoupling": 3.8946352
        },
        {
          "type": "WORK",
          "label": "120s@103w88rpm",
          "duration_secs": 120,
          "avg_power": 101,
          "max_power": 222,
          "avg_hr": 123,
          "max_hr": 148,
          "avg_cadence": 86.60833,
          "zone": 1,
          "training_load": 1.0083333,
          "decoupling": -18.963333
        },
        {
          "type": "WORK",
          "label": "180s@213w94rpm",
          "duration_secs": 180,
          "avg_power": 216,
          "max_power": 285,
          "avg_hr": 138,
          "max_hr": 151,
          "avg_cadence": 94.25,
          "zone": 3,
          "training_load": 3.86467,
          "decoupling": 9.830636
        },
        {
          "type": "WORK",
          "label": "120s@131w93rpm",
          "duration_secs": 120,
          "avg_power": 130,
          "max_power": 215,
          "avg_hr": 131,
          "max_hr": 150,
          "avg_cadence": 92.066666,
          "zone": 1,
          "training_load": 1.3020834,
          "decoupling": -11.479428
        },
        {
          "type": "WORK",
          "label": "180s@104w91rpm",
          "duration_secs": 180,
          "avg_power": 104,
          "max_power": 144,
          "avg_hr": 116,
          "max_hr": 126,
          "avg_cadence": 91.272224,
          "zone": 1,
          "training_load": 0.9938368,
          "decoupling": -2.0105772
        },
        {
          "type": "WORK",
          "label": "180s@171w94rpm",
          "duration_secs": 180,
          "avg_power": 180,
          "max_power": 223,
          "avg_hr": 133,
          "max_hr": 142,
          "avg_cadence": 96.744446,
          "zone": 2,
          "training_load": 2.6888888,
          "decoupling": 6.4266295
        },
        {
          "type": "WORK",
          "label": "120s@185w92rpm",
          "duration_secs": 120,
          "avg_power": 186,
          "max_power": 242,
          "avg_hr": 142,
          "max_hr": 149,
          "avg_cadence": 90.566666,
          "zone": 2,
          "training_load": 2.0891204,
          "decoupling": 2.5852463
        },
        {
          "type": "WORK",
          "label": "180s@213w94rpm",
          "duration_secs": 180,
          "avg_power": 205,
          "max_power": 250,
          "avg_hr": 145,
          "max_hr": 160,
          "avg_cadence": 91.994446,
          "zone": 3,
          "training_load": 3.6836805,
          "decoupling": 6.876223
        },
        {
          "type": "WORK",
          "label": "120s@103w88rpm",
          "duration_secs": 120,
          "avg_power": 105,
          "max_power": 193,
          "avg_hr": 128,
          "max_hr": 150,
          "avg_cadence": 89.64167,
          "zone": 1,
          "training_load": 1.0083333,
          "decoupling": -14.8237505
        },
        {
          "type": "WORK",
          "label": "180s@213w94rpm",
          "duration_secs": 180,
          "avg_power": 215,
          "max_power": 269,
          "avg_hr": 140,
          "max_hr": 156,
          "avg_cadence": 95.07222,
          "zone": 3,
          "training_load": 3.828125,
          "decoupling": 12.781232
        },
        {
          "type": "WORK",
          "label": "120s@131w93rpm",
          "duration_secs": 120,
          "avg_power": 131,
          "max_power": 182,
          "avg_hr": 133,
          "max_hr": 155,
          "avg_cadence": 93.666664,
          "zone": 1,
          "training_load": 1.2675925,
          "decoupling": -12.253247
        },
        {
          "type": "WORK",
          "label": "180s@171w94rpm",
          "duration_secs": 180,
          "avg_power": 167,
          "max_power": 198,
          "avg_hr": 125,
          "max_hr": 132,
          "avg_cadence": 94.638885,
          "zone": 1,
          "training_load": 2.3632812,
          "decoupling": 5.2731442
        },
        {
          "type": "WORK",
          "label": "60s@131w92rpm",
          "duration_secs": 60,
          "avg_power": 131,
          "max_power": 171,
          "avg_hr": 124,
          "max_hr": 131,
          "avg_cadence": 91.85,
          "zone": 1,
          "training_load": 0.58344907,
          "decoupling": 0.4029161
        },
        {
          "type": "WORK",
          "label": "60s@104w90rpm",
          "duration_secs": 59,
          "avg_power": 102,
          "max_power": 131,
          "avg_hr": 114,
          "max_hr": 118,
          "avg_cadence": 90.42373,
          "zone": 1,
          "training_load": 0.35691357,
          "decoupling": 4.74834
        }
      ]
    }
  ]
}